CHANGES.txt
LICENSE.txt
MANIFEST.in
README.rst
setup.py
jsonsyntax/__init__.py
jsonsyntax/jsonsyntax.py
test/test_jsonsyntax.py
ujs_jsonsyntax.egg-info/PKG-INFO
ujs_jsonsyntax.egg-info/SOURCES.txt
ujs_jsonsyntax.egg-info/dependency_links.txt
ujs_jsonsyntax.egg-info/entry_points.txt
ujs_jsonsyntax.egg-info/top_level.txt