Metadata-Version: 1.1
Name: ujs-jsonsyntax
Version: 0.1.0
Summary: JSON syntax checker
Home-page: http://github.com/usingjsonschema/ujs-jsonsyntax-python
Author: Joe McIntyre
Author-email: j_h_mcintyre@yahoo.com
License: MIT
Keywords: bookujs json
Platform: UNKNOWN
Classifier: Development Status :: 4 - Beta
Classifier: Environment :: Console
Classifier: License :: OSI Approved :: MIT License
Classifier: Operating System :: OS Independent
Classifier: Programming Language :: Python
Classifier: Programming Language :: Python :: 2
Classifier: Programming Language :: Python :: 2.7
Classifier: Programming Language :: Python :: 3
Classifier: Programming Language :: Python :: 3.4
Classifier: Intended Audience :: Developers
Classifier: Intended Audience :: System Administrators
Classifier: Topic :: Software Development
